{
  "name": "Adele Hanson",
  "age": 31,
  "address": {
    "street": "Pimec Court",
    "city": "Lujali",
    "state": "WY",
    "zip": "52137"
  },
  "contact": {
    "phone": "(833) 348-7745",
    "servicePhone": "800623555"
  },
  "birthday": "1961-08-25T20:38:56.021Z",
  "ip": "229.153.109.109",
  "foo": "bar",
  "profile": {
    "about": "Ducormim bawzuh zuzwo uki note ar kicta bo jos azle bujced jaculo gifohjo sa buzvadi ced lerfalu odore. Faojuopu monbidbi mirseb jo vottan facved zid idhibal hetsel wo safeam bizecce li sar. Ovsebkeg dowopuh paruhgis subafi wensemij ham ruj jevusa ud zoma wuje canun. Mod orenonci wow cureg ludmeeku jepmadow elevuc judaopu udefo jipaz valisad coezu. Sawilo sadlufur ju mok ezoemo iw vak dosvo jacuc wabota usovu mumhojsim ecefoob. Majovdop nisujor rabzegit puf nu sokeze fatlijov kevek oguzocji zasu ak nigzi ici var beikiov le.",
    "bio": "Ma vutibaj semveizo kitwipu songocik lafvot kut em kisvidkol gohir zid ibfulap afiuse zidub. Ih cijujfe vasimi jodre kesnaz pe hezaz piphi vi zeju diejibi bohapga toki mowmap kof fif gacrur uv. Iz po retwoh la nej cucfunu vu nu vedjuc ocarug mu rannu kuha polfa ne hi. Put fapbum so kofono ceitho bagbo bugud ni be ihi bo femuz. Mafoz peknup ep azuker oho ujosadek no uhoma acke fu muibe vu pitgubazi sizel. Ej cezit pozesas resutiho damzephe arnihi hivtopkih covzula daw fahujgej ajjupan lilem vegunaz riga new lov."
  },
  "apiKey": "466b3babbcb53f7560d049c86bfd936a02e2abb62374977f6e784025bbc5a3d5",
  "currency": {
    "code": "BGN",
    "name": "Bulgaria Lev"
  }
}