{
  "name": "Oscar Collins",
  "age": 60,
  "address": {
    "street": "Fedme Grove",
    "city": "Lezpirez",
    "state": "KY",
    "zip": "81204"
  },
  "contact": {
    "phone": "(984) 345-5596",
    "servicePhone": "800533695"
  },
  "birthday": "1993-10-06T23:43:04.616Z",
  "ip": "19.190.243.82",
  "foo": "bar",
  "profile": {
    "about": "Viite dubzoig gilaf tasbapeh ompil jodejus ol el uh lilapo rur ci ijpidda kicpiuje ka guves dugsej. Bibfafham jev opekuwil jitvuil jofigpak livzu ves jinaj macudcug neice jafu johug foel jowuw. Ugwef rozveh hitwur ale jet imapocwor acwukvid midzebu minher odlodur fo bukif lewehni. Kebugri heovuleb del bejom taf hizpoodu sazsehkih jaugapu vil naarke mefa se.",
    "bio": "Maz wufukwej wo fete dib zozi fojfajona kevor si wosowrul zuhan lu don botleve ok. Bes cajusa ikerup fukezja mewwig fokduvi fus er ce ravwavvaf memipraf peugnaz sassew. Ewtepda tis ro vine guh durasi zojzu sewalun lekfa wo acu tubtenuc daz ceh fuwivma gefro udi. Ke sofpu perjac bo socajher emwo fajal tecba teztebeve tabin ureru fahpuz ekane mibem hijnih keipu."
  },
  "apiKey": "ed6590756880962122bdbf8c119c90ef2d2ccd2d106d9550c626dc3db0e6072d",
  "currency": {
    "code": "IDR",
    "name": "Indonesia Rupiah"
  }
}